{"nhits": 26, "parameters": {"dataset": "outages-per-geography", "rows": 10, "start": 0, "facet": ["zipcode", "municipality"], "format": "json", "timezone": "UTC"}, "records": [{"datasetid": "outages-per-geography", "recordid": "73be768cace9f00cf0521944dd166ae0a07e1728", "fields": {"municipality": "Soure", "extractiondatetime": "2024-08-18T20:40:00+00:00", "zipcode": "3140-095", "municipalitycode": "0615", "interrupcao_ativa": 1}}, {"datasetid": "outages-per-geography", "recordid": "7c438f85fd7cc83080fcb1889bed0597eaae952e", "fields": {"municipality": "Soure", "extractiondatetime": "2024-08-18T20:40:00+00:00", "zipcode": "3140-146", "municipalitycode": "0615", "interrupcao_ativa": 1}}, {"datasetid": "outages-per-geography", "recordid": "3b9152f5546b72f00b4b640692a305fb447b6b76", "fields": {"municipality": "Soure", "extractiondatetime": "2024-08-18T20:40:00+00:00", "zipcode": "3140-201", "municipalitycode": "0615", "interrupcao_ativa": 1}}, {"datasetid": "outages-per-geography", "recordid": "e7769bb7d8d26982a6683d74cfa0fe03536c0ec8", "fields": {"municipality": "Soure", "extractiondatetime": "2024-08-18T20:40:00+00:00", "zipcode": "3140-207", "municipalitycode": "0615", "interrupcao_ativa": 1}}, {"datasetid": "outages-per-geography", "recordid": "319e3908d3463b9ff61d4b828dcb14ea14ca678b", "fields": {"municipality": "Soure", "extractiondatetime": "2024-08-18T20:40:00+00:00", "zipcode": "3140-250", "municipalitycode": "0615", "interrupcao_ativa": 1}}, {"datasetid": "outages-per-geography", "recordid": "2be0b2f4dc49e2b06b0f82dcdbb799f18f151795", "fields": {"municipality": "Soure", "extractiondatetime": "2024-08-18T20:40:00+00:00", "zipcode": "3140-263", "municipalitycode": "0615", "interrupcao_ativa": 1}}, {"datasetid": "outages-per-geography", "recordid": "225d011e9bbdec6261840ae54e3e526af7620d99", "fields": {"municipality": "Soure", "extractiondatetime": "2024-08-18T20:40:00+00:00", "zipcode": "3140-271", "municipalitycode": "0615", "interrupcao_ativa": 1}}, {"datasetid": "outages-per-geography", "recordid": "abf68755c661bd22098ac25955a58002893f64fa", "fields": {"municipality": "Soure", "extractiondatetime": "2024-08-18T20:40:00+00:00", "zipcode": "3140-274", "municipalitycode": "0615", "interrupcao_ativa": 1}}, {"datasetid": "outages-per-geography", "recordid": "418a220fb082e590466122124ce9082ffb03d023", "fields": {"municipality": "Soure", "extractiondatetime": "2024-08-18T20:40:00+00:00", "zipcode": "3140-445", "municipalitycode": "0615", "interrupcao_ativa": 1}}, {"datasetid": "outages-per-geography", "recordid": "1b967ebdde21f356521e2c412cb5c983faf0f740", "fields": {"municipality": "Soure", "extractiondatetime": "2024-08-18T20:40:00+00:00", "zipcode": "3140-148", "municipalitycode": "0615", "interrupcao_ativa": 1}}], "facet_groups": [{"name": "zipcode", "facets": [{"name": "3130-080", "count": 1, "state": "displayed", "path": "3130-080"}, {"name": "3140-095", "count": 1, "state": "displayed", "path": "3140-095"}, {"name": "3140-122", "count": 1, "state": "displayed", "path": "3140-122"}, {"name": "3140-146", "count": 1, "state": "displayed", "path": "3140-146"}, {"name": "3140-148", "count": 1, "state": "displayed", "path": "3140-148"}, {"name": "3140-201", "count": 1, "state": "displayed", "path": "3140-201"}, {"name": "3140-202", "count": 1, "state": "displayed", "path": "3140-202"}, {"name": "3140-203", "count": 1, "state": "displayed", "path": "3140-203"}, {"name": "3140-206", "count": 1, "state": "displayed", "path": "3140-206"}, {"name": "3140-207", "count": 1, "state": "displayed", "path": "3140-207"}, {"name": "3140-209", "count": 1, "state": "displayed", "path": "3140-209"}, {"name": "3140-249", "count": 1, "state": "displayed", "path": "3140-249"}, {"name": "3140-250", "count": 1, "state": "displayed", "path": "3140-250"}, {"name": "3140-257", "count": 1, "state": "displayed", "path": "3140-257"}, {"name": "3140-259", "count": 1, "state": "displayed", "path": "3140-259"}, {"name": "3140-263", "count": 1, "state": "displayed", "path": "3140-263"}, {"name": "3140-271", "count": 1, "state": "displayed", "path": "3140-271"}, {"name": "3140-272", "count": 1, "state": "displayed", "path": "3140-272"}, {"name": "3140-274", "count": 1, "state": "displayed", "path": "3140-274"}, {"name": "3140-282", "count": 1, "state": "displayed", "path": "3140-282"}, {"name": "3140-436", "count": 1, "state": "displayed", "path": "3140-436"}, {"name": "3140-442", "count": 1, "state": "displayed", "path": "3140-442"}, {"name": "3140-445", "count": 1, "state": "displayed", "path": "3140-445"}, {"name": "3140-446", "count": 1, "state": "displayed", "path": "3140-446"}, {"name": "3140-447", "count": 1, "state": "displayed", "path": "3140-447"}, {"name": "3140-455", "count": 1, "state": "displayed", "path": "3140-455"}]}, {"name": "municipality", "facets": [{"name": "Soure", "count": 26, "state": "displayed", "path": "Soure"}]}]}