{"nhits": 41, "parameters": {"dataset": "outages-per-geography", "rows": 10, "start": 20, "facet": ["zipcode", "municipality"], "format": "json", "timezone": "UTC"}, "records": [{"datasetid": "outages-per-geography", "recordid": "5b31caffeef090343e12231924d7967b37d3a324", "fields": {"municipality": "Loul\u00e9", "extractiondatetime": "2025-11-01T14:56:00+00:00", "zipcode": "8125-212", "municipalitycode": "0808", "interrupcao_ativa": 1}}, {"datasetid": "outages-per-geography", "recordid": "3856665803aa868842c6ed012f72b95f7380a295", "fields": {"municipality": "Loul\u00e9", "extractiondatetime": "2025-11-01T14:56:00+00:00", "zipcode": "8125-230", "municipalitycode": "0808", "interrupcao_ativa": 1}}, {"datasetid": "outages-per-geography", "recordid": "6fdaa75d1e7d64946a410a36bc6eed4b0703b0ce", "fields": {"municipality": "Loul\u00e9", "extractiondatetime": "2025-11-01T14:56:00+00:00", "zipcode": "8125-613", "municipalitycode": "0808", "interrupcao_ativa": 1}}, {"datasetid": "outages-per-geography", "recordid": "597fde918ddf151d49b84b152e4f9b5aaa749933", "fields": {"municipality": "Loul\u00e9", "extractiondatetime": "2025-11-01T14:56:00+00:00", "zipcode": "8125-633", "municipalitycode": "0808", "interrupcao_ativa": 1}}, {"datasetid": "outages-per-geography", "recordid": "6d39d6d02c849c5ed308ed5ef11ae550f43bc778", "fields": {"municipality": "Loul\u00e9", "extractiondatetime": "2025-11-01T14:56:00+00:00", "zipcode": "8125-710", "municipalitycode": "0808", "interrupcao_ativa": 1}}, {"datasetid": "outages-per-geography", "recordid": "ffbef61b2a5a8c275eee7abc4b0897cb7d0f37c1", "fields": {"municipality": "Loul\u00e9", "extractiondatetime": "2025-11-01T14:56:00+00:00", "zipcode": "8125-011", "municipalitycode": "0808", "interrupcao_ativa": 1}}, {"datasetid": "outages-per-geography", "recordid": "6cf686175609aa42d237f78ab674f3128e7896fd", "fields": {"municipality": "Loul\u00e9", "extractiondatetime": "2025-11-01T14:56:00+00:00", "zipcode": "8125-093", "municipalitycode": "0808", "interrupcao_ativa": 1}}, {"datasetid": "outages-per-geography", "recordid": "a01af711a4cf35d68a27b4ae85fb2c8e329c2a15", "fields": {"municipality": "Loul\u00e9", "extractiondatetime": "2025-11-01T14:56:00+00:00", "zipcode": "8125-110", "municipalitycode": "0808", "interrupcao_ativa": 1}}, {"datasetid": "outages-per-geography", "recordid": "28e5bcf0cda3e5185e1a0d7a429805107787701d", "fields": {"municipality": "Loul\u00e9", "extractiondatetime": "2025-11-01T14:56:00+00:00", "zipcode": "8125-112", "municipalitycode": "0808", "interrupcao_ativa": 1}}, {"datasetid": "outages-per-geography", "recordid": "070ca3f5629541ee462ff6e260fe96d217cf47a9", "fields": {"municipality": "Loul\u00e9", "extractiondatetime": "2025-11-01T14:56:00+00:00", "zipcode": "8125-116", "municipalitycode": "0808", "interrupcao_ativa": 1}}], "facet_groups": [{"name": "zipcode", "facets": [{"name": "8125-011", "count": 1, "state": "displayed", "path": "8125-011"}, {"name": "8125-090", "count": 1, "state": "displayed", "path": "8125-090"}, {"name": "8125-093", "count": 1, "state": "displayed", "path": "8125-093"}, {"name": "8125-105", "count": 1, "state": "displayed", "path": "8125-105"}, {"name": "8125-110", "count": 1, "state": "displayed", "path": "8125-110"}, {"name": "8125-112", "count": 1, "state": "displayed", "path": "8125-112"}, {"name": "8125-114", "count": 1, "state": "displayed", "path": "8125-114"}, {"name": "8125-116", "count": 1, "state": "displayed", "path": "8125-116"}, {"name": "8125-124", "count": 1, "state": "displayed", "path": "8125-124"}, {"name": "8125-165", "count": 1, "state": "displayed", "path": "8125-165"}, {"name": "8125-170", "count": 1, "state": "displayed", "path": "8125-170"}, {"name": "8125-171", "count": 1, "state": "displayed", "path": "8125-171"}, {"name": "8125-180", "count": 1, "state": "displayed", "path": "8125-180"}, {"name": "8125-181", "count": 1, "state": "displayed", "path": "8125-181"}, {"name": "8125-207", "count": 1, "state": "displayed", "path": "8125-207"}, {"name": "8125-212", "count": 1, "state": "displayed", "path": "8125-212"}, {"name": "8125-221", "count": 1, "state": "displayed", "path": "8125-221"}, {"name": "8125-222", "count": 1, "state": "displayed", "path": "8125-222"}, {"name": "8125-223", "count": 1, "state": "displayed", "path": "8125-223"}, {"name": "8125-225", "count": 1, "state": "displayed", "path": "8125-225"}, {"name": "8125-227", "count": 1, "state": "displayed", "path": "8125-227"}, {"name": "8125-230", "count": 1, "state": "displayed", "path": "8125-230"}, {"name": "8125-233", "count": 1, "state": "displayed", "path": "8125-233"}, {"name": "8125-241", "count": 1, "state": "displayed", "path": "8125-241"}, {"name": "8125-242", "count": 1, "state": "displayed", "path": "8125-242"}, {"name": "8125-244", "count": 1, "state": "displayed", "path": "8125-244"}, {"name": "8125-245", "count": 1, "state": "displayed", "path": "8125-245"}, {"name": "8125-248", "count": 1, "state": "displayed", "path": "8125-248"}, {"name": "8125-249", "count": 1, "state": "displayed", "path": "8125-249"}, {"name": "8125-251", "count": 1, "state": "displayed", "path": "8125-251"}, {"name": "8125-256", "count": 1, "state": "displayed", "path": "8125-256"}, {"name": "8125-257", "count": 1, "state": "displayed", "path": "8125-257"}, {"name": "8125-303", "count": 1, "state": "displayed", "path": "8125-303"}, {"name": "8125-307", "count": 1, "state": "displayed", "path": "8125-307"}, {"name": "8125-420", "count": 1, "state": "displayed", "path": "8125-420"}, {"name": "8125-592", "count": 1, "state": "displayed", "path": "8125-592"}, {"name": "8125-605", "count": 1, "state": "displayed", "path": "8125-605"}, {"name": "8125-613", "count": 1, "state": "displayed", "path": "8125-613"}, {"name": "8125-623", "count": 1, "state": "displayed", "path": "8125-623"}, {"name": "8125-633", "count": 1, "state": "displayed", "path": "8125-633"}, {"name": "8125-710", "count": 1, "state": "displayed", "path": "8125-710"}]}, {"name": "municipality", "facets": [{"name": "Loul\u00e9", "count": 41, "state": "displayed", "path": "Loul\u00e9"}]}]}