{"nhits": 190, "parameters": {"dataset": "outages-per-geography", "rows": 10, "start": 20, "facet": ["zipcode", "municipality"], "format": "json", "timezone": "UTC"}, "records": [{"datasetid": "outages-per-geography", "recordid": "a839a7b7b917ee489bc0156c798b86e426f3e766", "fields": {"municipality": "Cascais", "extractiondatetime": "2025-05-20T18:26:00+00:00", "zipcode": "2780-054", "municipalitycode": "1105", "interrupcao_ativa": 1}}, {"datasetid": "outages-per-geography", "recordid": "a8573b9015e7d549ccced9eb34f47e5423382c85", "fields": {"municipality": "Cascais", "extractiondatetime": "2025-05-20T18:26:00+00:00", "zipcode": "2780-080", "municipalitycode": "1105", "interrupcao_ativa": 1}}, {"datasetid": "outages-per-geography", "recordid": "631238d8938d0f4dd975ea02d6a6fdb6e4c88cf2", "fields": {"municipality": "Cascais", "extractiondatetime": "2025-05-20T18:26:00+00:00", "zipcode": "2780-087", "municipalitycode": "1105", "interrupcao_ativa": 1}}, {"datasetid": "outages-per-geography", "recordid": "7c260446343ace4bf177ebfd6928e0433747921f", "fields": {"municipality": "Cascais", "extractiondatetime": "2025-05-20T18:26:00+00:00", "zipcode": "2780-093", "municipalitycode": "1105", "interrupcao_ativa": 1}}, {"datasetid": "outages-per-geography", "recordid": "ebc78b19913e5e57b3fcebebdd2d30c0651b2ffe", "fields": {"municipality": "Cascais", "extractiondatetime": "2025-05-20T18:26:00+00:00", "zipcode": "2780-123", "municipalitycode": "1105", "interrupcao_ativa": 1}}, {"datasetid": "outages-per-geography", "recordid": "84735d2f1ff9df1b8b1cfb620468d7e599d9ce5b", "fields": {"municipality": "Cascais", "extractiondatetime": "2025-05-20T18:26:00+00:00", "zipcode": "2780-124", "municipalitycode": "1105", "interrupcao_ativa": 1}}, {"datasetid": "outages-per-geography", "recordid": "0b24a2064fd4659407e822e915474833ec3def4e", "fields": {"municipality": "Cascais", "extractiondatetime": "2025-05-20T18:26:00+00:00", "zipcode": "2780-130", "municipalitycode": "1105", "interrupcao_ativa": 1}}, {"datasetid": "outages-per-geography", "recordid": "370b1ab8f6eb0350fd89eba3d5ff33fbc12ee8c1", "fields": {"municipality": "Cascais", "extractiondatetime": "2025-05-20T18:26:00+00:00", "zipcode": "2780-149", "municipalitycode": "1105", "interrupcao_ativa": 1}}, {"datasetid": "outages-per-geography", "recordid": "09b887d0028d69e857fbb6f9c563886786f0e08d", "fields": {"municipality": "Cascais", "extractiondatetime": "2025-05-20T18:26:00+00:00", "zipcode": "2780-170", "municipalitycode": "1105", "interrupcao_ativa": 1}}, {"datasetid": "outages-per-geography", "recordid": "cac9df0f514388f18d28a843d65c5a5c0d3c92fd", "fields": {"municipality": "Cascais", "extractiondatetime": "2025-05-20T18:26:00+00:00", "zipcode": "2780-191", "municipalitycode": "1105", "interrupcao_ativa": 1}}], "facet_groups": [{"name": "zipcode", "facets": [{"name": "2760-005", "count": 1, "state": "displayed", "path": "2760-005"}, {"name": "2760-007", "count": 1, "state": "displayed", "path": "2760-007"}, {"name": "2760-010", "count": 1, "state": "displayed", "path": "2760-010"}, {"name": "2760-016", "count": 1, "state": "displayed", "path": "2760-016"}, {"name": "2760-018", "count": 1, "state": "displayed", "path": "2760-018"}, {"name": "2760-030", "count": 1, "state": "displayed", "path": "2760-030"}, {"name": "2760-031", "count": 1, "state": "displayed", "path": "2760-031"}, {"name": "2760-032", "count": 1, "state": "displayed", "path": "2760-032"}, {"name": "2760-033", "count": 1, "state": "displayed", "path": "2760-033"}, {"name": "2760-035", "count": 1, "state": "displayed", "path": "2760-035"}, {"name": "2760-037", "count": 1, "state": "displayed", "path": "2760-037"}, {"name": "2760-038", "count": 1, "state": "displayed", "path": "2760-038"}, {"name": "2760-041", "count": 1, "state": "displayed", "path": "2760-041"}, {"name": "2760-043", "count": 1, "state": "displayed", "path": "2760-043"}, {"name": "2760-045", "count": 1, "state": "displayed", "path": "2760-045"}, {"name": "2760-046", "count": 1, "state": "displayed", "path": "2760-046"}, {"name": "2760-048", "count": 1, "state": "displayed", "path": "2760-048"}, {"name": "2760-056", "count": 1, "state": "displayed", "path": "2760-056"}, {"name": "2760-065", "count": 1, "state": "displayed", "path": "2760-065"}, {"name": "2760-069", "count": 1, "state": "displayed", "path": "2760-069"}, {"name": "2760-075", "count": 1, "state": "displayed", "path": "2760-075"}, {"name": "2760-087", "count": 1, "state": "displayed", "path": "2760-087"}, {"name": "2760-089", "count": 1, "state": "displayed", "path": "2760-089"}, {"name": "2760-099", "count": 1, "state": "displayed", "path": "2760-099"}, {"name": "2760-108", "count": 1, "state": "displayed", "path": "2760-108"}, {"name": "2760-110", "count": 1, "state": "displayed", "path": "2760-110"}, {"name": "2760-119", "count": 1, "state": "displayed", "path": "2760-119"}, {"name": "2760-122", "count": 1, "state": "displayed", "path": "2760-122"}, {"name": "2760-157", "count": 1, "state": "displayed", "path": "2760-157"}, {"name": "2760-186", "count": 1, "state": "displayed", "path": "2760-186"}, {"name": "2770-007", "count": 1, "state": "displayed", "path": "2770-007"}, {"name": "2770-013", "count": 1, "state": "displayed", "path": "2770-013"}, {"name": "2770-032", "count": 1, "state": "displayed", "path": "2770-032"}, {"name": "2770-042", "count": 1, "state": "displayed", "path": "2770-042"}, {"name": "2770-043", "count": 1, "state": "displayed", "path": "2770-043"}, {"name": "2770-047", "count": 1, "state": "displayed", "path": "2770-047"}, {"name": "2770-049", "count": 1, "state": "displayed", "path": "2770-049"}, {"name": "2770-050", "count": 1, "state": "displayed", "path": "2770-050"}, {"name": "2770-051", "count": 1, "state": "displayed", "path": "2770-051"}, {"name": "2770-052", "count": 1, "state": "displayed", "path": "2770-052"}, {"name": "2770-055", "count": 1, "state": "displayed", "path": "2770-055"}, {"name": "2770-063", "count": 1, "state": "displayed", "path": "2770-063"}, {"name": "2770-067", "count": 1, "state": "displayed", "path": "2770-067"}, {"name": "2770-075", "count": 1, "state": "displayed", "path": "2770-075"}, {"name": "2770-082", "count": 1, "state": "displayed", "path": "2770-082"}, {"name": "2770-083", "count": 1, "state": "displayed", "path": "2770-083"}, {"name": "2770-093", "count": 1, "state": "displayed", "path": "2770-093"}, {"name": "2770-101", "count": 1, "state": "displayed", "path": "2770-101"}, {"name": "2770-112", "count": 1, "state": "displayed", "path": "2770-112"}, {"name": "2770-121", "count": 1, "state": "displayed", "path": "2770-121"}, {"name": "2770-123", "count": 1, "state": "displayed", "path": "2770-123"}, {"name": "2770-135", "count": 1, "state": "displayed", "path": "2770-135"}, {"name": "2770-142", "count": 1, "state": "displayed", "path": "2770-142"}, {"name": "2770-145", "count": 1, "state": "displayed", "path": "2770-145"}, {"name": "2770-146", "count": 1, "state": "displayed", "path": "2770-146"}, {"name": "2770-148", "count": 1, "state": "displayed", "path": "2770-148"}, {"name": "2770-161", "count": 1, "state": "displayed", "path": "2770-161"}, {"name": "2770-162", "count": 1, "state": "displayed", "path": "2770-162"}, {"name": "2770-163", "count": 1, "state": "displayed", "path": "2770-163"}, {"name": "2770-164", "count": 1, "state": "displayed", "path": "2770-164"}, {"name": "2770-169", "count": 1, "state": "displayed", "path": "2770-169"}, {"name": "2770-176", "count": 1, "state": "displayed", "path": "2770-176"}, {"name": "2770-179", "count": 1, "state": "displayed", "path": "2770-179"}, {"name": "2770-180", "count": 1, "state": "displayed", "path": "2770-180"}, {"name": "2770-181", "count": 1, "state": "displayed", "path": "2770-181"}, {"name": "2770-183", "count": 1, "state": "displayed", "path": "2770-183"}, {"name": "2770-204", "count": 1, "state": "displayed", "path": "2770-204"}, {"name": "2770-206", "count": 1, "state": "displayed", "path": "2770-206"}, {"name": "2770-208", "count": 1, "state": "displayed", "path": "2770-208"}, {"name": "2770-210", "count": 1, "state": "displayed", "path": "2770-210"}, {"name": "2770-213", "count": 1, "state": "displayed", "path": "2770-213"}, {"name": "2770-214", "count": 1, "state": "displayed", "path": "2770-214"}, {"name": "2770-232", "count": 1, "state": "displayed", "path": "2770-232"}, {"name": "2775-396", "count": 1, "state": "displayed", "path": "2775-396"}, {"name": "2775-397", "count": 1, "state": "displayed", "path": "2775-397"}, {"name": "2775-401", "count": 1, "state": "displayed", "path": "2775-401"}, {"name": "2775-405", "count": 1, "state": "displayed", "path": "2775-405"}, {"name": "2775-419", "count": 1, "state": "displayed", "path": "2775-419"}, {"name": "2775-621", "count": 1, "state": "displayed", "path": "2775-621"}, {"name": "2775-629", "count": 1, "state": "displayed", "path": "2775-629"}, {"name": "2775-630", "count": 1, "state": "displayed", "path": "2775-630"}, {"name": "2775-675", "count": 1, "state": "displayed", "path": "2775-675"}, {"name": "2775-681", "count": 1, "state": "displayed", "path": "2775-681"}, {"name": "2775-684", "count": 1, "state": "displayed", "path": "2775-684"}, {"name": "2780-003", "count": 1, "state": "displayed", "path": "2780-003"}, {"name": "2780-009", "count": 1, "state": "displayed", "path": "2780-009"}, {"name": "2780-015", "count": 1, "state": "displayed", "path": "2780-015"}, {"name": "2780-051", "count": 1, "state": "displayed", "path": "2780-051"}, {"name": "2780-052", "count": 1, "state": "displayed", "path": "2780-052"}, {"name": "2780-054", "count": 1, "state": "displayed", "path": "2780-054"}, {"name": "2780-056", "count": 1, "state": "displayed", "path": "2780-056"}, {"name": "2780-060", "count": 1, "state": "displayed", "path": "2780-060"}, {"name": "2780-065", "count": 1, "state": "displayed", "path": "2780-065"}, {"name": "2780-068", "count": 1, "state": "displayed", "path": "2780-068"}, {"name": "2780-080", "count": 1, "state": "displayed", "path": "2780-080"}, {"name": "2780-084", "count": 1, "state": "displayed", "path": "2780-084"}, {"name": "2780-085", "count": 1, "state": "displayed", "path": "2780-085"}, {"name": "2780-087", "count": 1, "state": "displayed", "path": "2780-087"}, {"name": "2780-089", "count": 1, "state": "displayed", "path": "2780-089"}, {"name": "2780-093", "count": 1, "state": "displayed", "path": "2780-093"}]}, {"name": "municipality", "facets": [{"name": "Cascais", "count": 190, "state": "displayed", "path": "Cascais"}]}]}