{"nhits": 1, "parameters": {"dataset": "outages-per-geography", "rows": 10, "start": 0, "facet": ["zipcode", "municipality"], "format": "json", "timezone": "UTC"}, "records": [{"datasetid": "outages-per-geography", "recordid": "3ce2dedc85a7f3fbcc763629eb9c299a8a3a5c17", "fields": {"extractiondatetime": "2023-05-16T19:15:00+00:00", "zipcode": "8970-311", "municipality": "Alcoutim"}, "record_timestamp": "2023-05-16T18:30:07.215Z"}], "facet_groups": [{"name": "zipcode", "facets": [{"name": "8970-311", "count": 1, "state": "displayed", "path": "8970-311"}]}, {"name": "municipality", "facets": [{"name": "Alcoutim", "count": 1, "state": "displayed", "path": "Alcoutim"}]}]}