{"nhits": 36, "parameters": {"dataset": "outages-per-geography", "rows": 10, "start": 30, "facet": ["zipcode", "municipality"], "format": "json", "timezone": "UTC"}, "records": [{"datasetid": "outages-per-geography", "recordid": "b08bbe9eae7d0f0f95a95601cffe8bd16298044f", "fields": {"municipality": "Lisboa", "extractiondatetime": "2023-11-22T23:34:00+00:00", "zipcode": "1200-301", "interrupcao_ativa": 1}}, {"datasetid": "outages-per-geography", "recordid": "2a7e857f07e2f243b7d6806de0839a7e84e05146", "fields": {"municipality": "Lisboa", "extractiondatetime": "2023-11-22T23:34:00+00:00", "zipcode": "1200-303", "interrupcao_ativa": 1}}, {"datasetid": "outages-per-geography", "recordid": "cc44916eb3922ddaeaf33846c88234ad025b37fd", "fields": {"municipality": "Lisboa", "extractiondatetime": "2023-11-22T23:34:00+00:00", "zipcode": "1200-308", "interrupcao_ativa": 1}}, {"datasetid": "outages-per-geography", "recordid": "e11e201c942599dd3d8b526e21579520240af617", "fields": {"municipality": "Lisboa", "extractiondatetime": "2023-11-22T23:34:00+00:00", "zipcode": "1200-365", "interrupcao_ativa": 1}}, {"datasetid": "outages-per-geography", "recordid": "6ef227901ed64150ef6ae9314cd5cbc33146349c", "fields": {"municipality": "Lisboa", "extractiondatetime": "2023-11-22T23:34:00+00:00", "zipcode": "1200-382", "interrupcao_ativa": 1}}, {"datasetid": "outages-per-geography", "recordid": "1485af01e45de6f076850818db75918b416a1c28", "fields": {"municipality": "Lisboa", "extractiondatetime": "2023-11-22T23:34:00+00:00", "zipcode": "1200-470", "interrupcao_ativa": 1}}], "facet_groups": [{"name": "zipcode", "facets": [{"name": "1200-036", "count": 1, "state": "displayed", "path": "1200-036"}, {"name": "1200-041", "count": 1, "state": "displayed", "path": "1200-041"}, {"name": "1200-042", "count": 1, "state": "displayed", "path": "1200-042"}, {"name": "1200-047", "count": 1, "state": "displayed", "path": "1200-047"}, {"name": "1200-048", "count": 1, "state": "displayed", "path": "1200-048"}, {"name": "1200-051", "count": 1, "state": "displayed", "path": "1200-051"}, {"name": "1200-090", "count": 1, "state": "displayed", "path": "1200-090"}, {"name": "1200-091", "count": 1, "state": "displayed", "path": "1200-091"}, {"name": "1200-121", "count": 1, "state": "displayed", "path": "1200-121"}, {"name": "1200-122", "count": 1, "state": "displayed", "path": "1200-122"}, {"name": "1200-142", "count": 1, "state": "displayed", "path": "1200-142"}, {"name": "1200-143", "count": 1, "state": "displayed", "path": "1200-143"}, {"name": "1200-145", "count": 1, "state": "displayed", "path": "1200-145"}, {"name": "1200-155", "count": 1, "state": "displayed", "path": "1200-155"}, {"name": "1200-156", "count": 1, "state": "displayed", "path": "1200-156"}, {"name": "1200-158", "count": 1, "state": "displayed", "path": "1200-158"}, {"name": "1200-159", "count": 1, "state": "displayed", "path": "1200-159"}, {"name": "1200-187", "count": 1, "state": "displayed", "path": "1200-187"}, {"name": "1200-235", "count": 1, "state": "displayed", "path": "1200-235"}, {"name": "1200-247", "count": 1, "state": "displayed", "path": "1200-247"}, {"name": "1200-248", "count": 1, "state": "displayed", "path": "1200-248"}, {"name": "1200-268", "count": 1, "state": "displayed", "path": "1200-268"}, {"name": "1200-271", "count": 1, "state": "displayed", "path": "1200-271"}, {"name": "1200-272", "count": 1, "state": "displayed", "path": "1200-272"}, {"name": "1200-273", "count": 1, "state": "displayed", "path": "1200-273"}, {"name": "1200-284", "count": 1, "state": "displayed", "path": "1200-284"}, {"name": "1200-301", "count": 1, "state": "displayed", "path": "1200-301"}, {"name": "1200-303", "count": 1, "state": "displayed", "path": "1200-303"}, {"name": "1200-308", "count": 1, "state": "displayed", "path": "1200-308"}, {"name": "1200-309", "count": 1, "state": "displayed", "path": "1200-309"}, {"name": "1200-365", "count": 1, "state": "displayed", "path": "1200-365"}, {"name": "1200-381", "count": 1, "state": "displayed", "path": "1200-381"}, {"name": "1200-382", "count": 1, "state": "displayed", "path": "1200-382"}, {"name": "1200-388", "count": 1, "state": "displayed", "path": "1200-388"}, {"name": "1200-396", "count": 1, "state": "displayed", "path": "1200-396"}, {"name": "1200-470", "count": 1, "state": "displayed", "path": "1200-470"}]}, {"name": "municipality", "facets": [{"name": "Lisboa", "count": 36, "state": "displayed", "path": "Lisboa"}]}]}