{"nhits": 12, "parameters": {"dataset": "outages-per-geography", "rows": 10, "start": 10, "facet": ["zipcode", "municipality"], "format": "json", "timezone": "UTC"}, "records": [{"datasetid": "outages-per-geography", "recordid": "fe0363c6b5ff2845bea29256ccec7c619fd31c12", "fields": {"municipality": "\u00d3bidos", "extractiondatetime": "2024-09-21T14:55:00+00:00", "zipcode": "2510-411", "municipalitycode": "1012", "interrupcao_ativa": 1}}, {"datasetid": "outages-per-geography", "recordid": "6cb44d66d73576ada8ec2065fd09308c53b2f20d", "fields": {"municipality": "\u00d3bidos", "extractiondatetime": "2024-09-21T14:55:00+00:00", "zipcode": "2510-455", "municipalitycode": "1012", "interrupcao_ativa": 1}}], "facet_groups": [{"name": "zipcode", "facets": [{"name": "2510-011", "count": 1, "state": "displayed", "path": "2510-011"}, {"name": "2510-018", "count": 1, "state": "displayed", "path": "2510-018"}, {"name": "2510-402", "count": 1, "state": "displayed", "path": "2510-402"}, {"name": "2510-405", "count": 1, "state": "displayed", "path": "2510-405"}, {"name": "2510-411", "count": 1, "state": "displayed", "path": "2510-411"}, {"name": "2510-414", "count": 1, "state": "displayed", "path": "2510-414"}, {"name": "2510-417", "count": 1, "state": "displayed", "path": "2510-417"}, {"name": "2510-425", "count": 1, "state": "displayed", "path": "2510-425"}, {"name": "2510-434", "count": 1, "state": "displayed", "path": "2510-434"}, {"name": "2510-441", "count": 1, "state": "displayed", "path": "2510-441"}, {"name": "2510-455", "count": 1, "state": "displayed", "path": "2510-455"}, {"name": "2510-651", "count": 1, "state": "displayed", "path": "2510-651"}]}, {"name": "municipality", "facets": [{"name": "\u00d3bidos", "count": 12, "state": "displayed", "path": "\u00d3bidos"}]}]}