{"nhits": 25, "parameters": {"dataset": "outages-per-geography", "rows": 10, "start": 10, "facet": ["zipcode", "municipality"], "format": "json", "timezone": "UTC"}, "records": [{"datasetid": "outages-per-geography", "recordid": "f51d3b74cafec51a2a3c5d3f9c04eb531fe945fa", "fields": {"municipality": "Tavira", "extractiondatetime": "2025-07-26T10:56:00+00:00", "zipcode": "8700-582", "municipalitycode": "0814", "interrupcao_ativa": 1}}, {"datasetid": "outages-per-geography", "recordid": "0c091cbae4988fb3fb213708518c70b93168dc11", "fields": {"municipality": "Tavira", "extractiondatetime": "2025-07-26T10:56:00+00:00", "zipcode": "8800-101", "municipalitycode": "0814", "interrupcao_ativa": 1}}, {"datasetid": "outages-per-geography", "recordid": "411bce05d97258b3f955c853913066d6459c95bb", "fields": {"municipality": "Tavira", "extractiondatetime": "2025-07-26T10:56:00+00:00", "zipcode": "8800-108", "municipalitycode": "0814", "interrupcao_ativa": 1}}, {"datasetid": "outages-per-geography", "recordid": "ddf694afb2d00a7e6edc6cb51d726b3b48af0c2e", "fields": {"municipality": "Tavira", "extractiondatetime": "2025-07-26T10:56:00+00:00", "zipcode": "8800-109", "municipalitycode": "0814", "interrupcao_ativa": 1}}, {"datasetid": "outages-per-geography", "recordid": "1623e51d4f19cb44f51f3d3dab0a62c3d4cedda1", "fields": {"municipality": "Tavira", "extractiondatetime": "2025-07-26T10:56:00+00:00", "zipcode": "8800-112", "municipalitycode": "0814", "interrupcao_ativa": 1}}, {"datasetid": "outages-per-geography", "recordid": "c9c0457ea2273313a5e4e4322299ea0f531cdfe0", "fields": {"municipality": "Tavira", "extractiondatetime": "2025-07-26T10:56:00+00:00", "zipcode": "8800-116", "municipalitycode": "0814", "interrupcao_ativa": 1}}, {"datasetid": "outages-per-geography", "recordid": "7ab0c9ac665723f3213111ed24c676722ea18e51", "fields": {"municipality": "Ponte de Lima", "extractiondatetime": "2025-07-26T10:56:00+00:00", "zipcode": "4990-580", "municipalitycode": "1607", "interrupcao_ativa": 1}}, {"datasetid": "outages-per-geography", "recordid": "bd8a339d9c8c6a504e097034351c568eaf8a065b", "fields": {"municipality": "Tavira", "extractiondatetime": "2025-07-26T10:56:00+00:00", "zipcode": "8700-078", "municipalitycode": "0814", "interrupcao_ativa": 1}}, {"datasetid": "outages-per-geography", "recordid": "5c99c4124ad7ae0662ff15a9e33c83c4d66c5e26", "fields": {"municipality": "Tavira", "extractiondatetime": "2025-07-26T10:56:00+00:00", "zipcode": "8800-102", "municipalitycode": "0814", "interrupcao_ativa": 1}}, {"datasetid": "outages-per-geography", "recordid": "1312ecc7bb1dd6fcae6797b3dce29cc19b48b658", "fields": {"municipality": "Tavira", "extractiondatetime": "2025-07-26T10:56:00+00:00", "zipcode": "8800-105", "municipalitycode": "0814", "interrupcao_ativa": 1}}], "facet_groups": [{"name": "zipcode", "facets": [{"name": "4990-500", "count": 1, "state": "displayed", "path": "4990-500"}, {"name": "4990-501", "count": 1, "state": "displayed", "path": "4990-501"}, {"name": "4990-519", "count": 1, "state": "displayed", "path": "4990-519"}, {"name": "4990-580", "count": 1, "state": "displayed", "path": "4990-580"}, {"name": "4990-635", "count": 1, "state": "displayed", "path": "4990-635"}, {"name": "4990-665", "count": 1, "state": "displayed", "path": "4990-665"}, {"name": "8700-078", "count": 1, "state": "displayed", "path": "8700-078"}, {"name": "8700-120", "count": 1, "state": "displayed", "path": "8700-120"}, {"name": "8700-121", "count": 1, "state": "displayed", "path": "8700-121"}, {"name": "8700-582", "count": 1, "state": "displayed", "path": "8700-582"}, {"name": "8800-101", "count": 1, "state": "displayed", "path": "8800-101"}, {"name": "8800-102", "count": 1, "state": "displayed", "path": "8800-102"}, {"name": "8800-105", "count": 1, "state": "displayed", "path": "8800-105"}, {"name": "8800-106", "count": 1, "state": "displayed", "path": "8800-106"}, {"name": "8800-108", "count": 1, "state": "displayed", "path": "8800-108"}, {"name": "8800-109", "count": 1, "state": "displayed", "path": "8800-109"}, {"name": "8800-110", "count": 1, "state": "displayed", "path": "8800-110"}, {"name": "8800-111", "count": 1, "state": "displayed", "path": "8800-111"}, {"name": "8800-112", "count": 1, "state": "displayed", "path": "8800-112"}, {"name": "8800-113", "count": 1, "state": "displayed", "path": "8800-113"}, {"name": "8800-116", "count": 1, "state": "displayed", "path": "8800-116"}, {"name": "8800-118", "count": 1, "state": "displayed", "path": "8800-118"}, {"name": "8800-120", "count": 1, "state": "displayed", "path": "8800-120"}, {"name": "8800-123", "count": 1, "state": "displayed", "path": "8800-123"}, {"name": "8800-513", "count": 1, "state": "displayed", "path": "8800-513"}]}, {"name": "municipality", "facets": [{"name": "Tavira", "count": 19, "state": "displayed", "path": "Tavira"}, {"name": "Ponte de Lima", "count": 6, "state": "displayed", "path": "Ponte de Lima"}]}]}