{"nhits": 53, "parameters": {"dataset": "outages-per-geography", "rows": 10, "start": 50, "facet": ["zipcode", "municipality"], "format": "json", "timezone": "UTC"}, "records": [{"datasetid": "outages-per-geography", "recordid": "84bf06e60e1663154e00626f2166c4dbba08297c", "fields": {"extractiondatetime": "2023-04-11T09:34:00+00:00", "zipcode": "2530-157", "municipality": "Lourinh\u00e3"}, "record_timestamp": "2023-04-11T08:45:01.571Z"}, {"datasetid": "outages-per-geography", "recordid": "40c66450862a1eef2098f9656ea0715c748f4b2c", "fields": {"extractiondatetime": "2023-04-11T09:34:00+00:00", "zipcode": "2530-158", "municipality": "Lourinh\u00e3"}, "record_timestamp": "2023-04-11T08:45:01.571Z"}, {"datasetid": "outages-per-geography", "recordid": "bb5877849f92d9114abc3afc21322b1612e13f62", "fields": {"extractiondatetime": "2023-04-11T09:34:00+00:00", "zipcode": "2530-875", "municipality": "Lourinh\u00e3"}, "record_timestamp": "2023-04-11T08:45:01.571Z"}], "facet_groups": [{"name": "zipcode", "facets": [{"name": "2530-009", "count": 1, "state": "displayed", "path": "2530-009"}, {"name": "2530-010", "count": 1, "state": "displayed", "path": "2530-010"}, {"name": "2530-011", "count": 1, "state": "displayed", "path": "2530-011"}, {"name": "2530-013", "count": 1, "state": "displayed", "path": "2530-013"}, {"name": "2530-014", "count": 1, "state": "displayed", "path": "2530-014"}, {"name": "2530-015", "count": 1, "state": "displayed", "path": "2530-015"}, {"name": "2530-022", "count": 1, "state": "displayed", "path": "2530-022"}, {"name": "2530-026", "count": 1, "state": "displayed", "path": "2530-026"}, {"name": "2530-036", "count": 1, "state": "displayed", "path": "2530-036"}, {"name": "2530-038", "count": 1, "state": "displayed", "path": "2530-038"}, {"name": "2530-049", "count": 1, "state": "displayed", "path": "2530-049"}, {"name": "2530-052", "count": 1, "state": "displayed", "path": "2530-052"}, {"name": "2530-057", "count": 1, "state": "displayed", "path": "2530-057"}, {"name": "2530-074", "count": 1, "state": "displayed", "path": "2530-074"}, {"name": "2530-099", "count": 1, "state": "displayed", "path": "2530-099"}, {"name": "2530-100", "count": 1, "state": "displayed", "path": "2530-100"}, {"name": "2530-101", "count": 1, "state": "displayed", "path": "2530-101"}, {"name": "2530-102", "count": 1, "state": "displayed", "path": "2530-102"}, {"name": "2530-103", "count": 1, "state": "displayed", "path": "2530-103"}, {"name": "2530-104", "count": 1, "state": "displayed", "path": "2530-104"}, {"name": "2530-106", "count": 1, "state": "displayed", "path": "2530-106"}, {"name": "2530-107", "count": 1, "state": "displayed", "path": "2530-107"}, {"name": "2530-108", "count": 1, "state": "displayed", "path": "2530-108"}, {"name": "2530-109", "count": 1, "state": "displayed", "path": "2530-109"}, {"name": "2530-110", "count": 1, "state": "displayed", "path": "2530-110"}, {"name": "2530-113", "count": 1, "state": "displayed", "path": "2530-113"}, {"name": "2530-114", "count": 1, "state": "displayed", "path": "2530-114"}, {"name": "2530-116", "count": 1, "state": "displayed", "path": "2530-116"}, {"name": "2530-125", "count": 1, "state": "displayed", "path": "2530-125"}, {"name": "2530-126", "count": 1, "state": "displayed", "path": "2530-126"}, {"name": "2530-128", "count": 1, "state": "displayed", "path": "2530-128"}, {"name": "2530-131", "count": 1, "state": "displayed", "path": "2530-131"}, {"name": "2530-132", "count": 1, "state": "displayed", "path": "2530-132"}, {"name": "2530-134", "count": 1, "state": "displayed", "path": "2530-134"}, {"name": "2530-135", "count": 1, "state": "displayed", "path": "2530-135"}, {"name": "2530-136", "count": 1, "state": "displayed", "path": "2530-136"}, {"name": "2530-137", "count": 1, "state": "displayed", "path": "2530-137"}, {"name": "2530-142", "count": 1, "state": "displayed", "path": "2530-142"}, {"name": "2530-144", "count": 1, "state": "displayed", "path": "2530-144"}, {"name": "2530-147", "count": 1, "state": "displayed", "path": "2530-147"}, {"name": "2530-148", "count": 1, "state": "displayed", "path": "2530-148"}, {"name": "2530-150", "count": 1, "state": "displayed", "path": "2530-150"}, {"name": "2530-151", "count": 1, "state": "displayed", "path": "2530-151"}, {"name": "2530-153", "count": 1, "state": "displayed", "path": "2530-153"}, {"name": "2530-154", "count": 1, "state": "displayed", "path": "2530-154"}, {"name": "2530-157", "count": 1, "state": "displayed", "path": "2530-157"}, {"name": "2530-158", "count": 1, "state": "displayed", "path": "2530-158"}, {"name": "2530-161", "count": 1, "state": "displayed", "path": "2530-161"}, {"name": "2530-178", "count": 1, "state": "displayed", "path": "2530-178"}, {"name": "2530-875", "count": 1, "state": "displayed", "path": "2530-875"}, {"name": "2530-921", "count": 1, "state": "displayed", "path": "2530-921"}, {"name": "2530-922", "count": 1, "state": "displayed", "path": "2530-922"}, {"name": "2530-929", "count": 1, "state": "displayed", "path": "2530-929"}]}, {"name": "municipality", "facets": [{"name": "Lourinh\u00e3", "count": 53, "state": "displayed", "path": "Lourinh\u00e3"}]}]}