{"nhits": 23, "parameters": {"dataset": "outages-per-geography", "rows": 10, "start": 0, "facet": ["zipcode", "municipality"], "format": "json", "timezone": "UTC"}, "records": [{"datasetid": "outages-per-geography", "recordid": "ff2151ecae2ef1d65bc4cc4d1d33f6676ba60796", "fields": {"municipality": "Barcelos", "extractiondatetime": "2024-04-01T17:18:00+00:00", "zipcode": "4750-125", "municipalitycode": "0302", "interrupcao_ativa": 1}}, {"datasetid": "outages-per-geography", "recordid": "605b94438c7a3dc42c49da1253fced3385ab4a96", "fields": {"municipality": "Barcelos", "extractiondatetime": "2024-04-01T17:18:00+00:00", "zipcode": "4750-166", "municipalitycode": "0302", "interrupcao_ativa": 1}}, {"datasetid": "outages-per-geography", "recordid": "4be0a02f8a3b4bbd41a38f8488876a2ef92d981b", "fields": {"municipality": "Barcelos", "extractiondatetime": "2024-04-01T17:18:00+00:00", "zipcode": "4750-464", "municipalitycode": "0302", "interrupcao_ativa": 1}}, {"datasetid": "outages-per-geography", "recordid": "a15573e298385b2f7a63df88fda5d9c1754a4c73", "fields": {"municipality": "Barcelos", "extractiondatetime": "2024-04-01T17:18:00+00:00", "zipcode": "4750-724", "municipalitycode": "0302", "interrupcao_ativa": 1}}, {"datasetid": "outages-per-geography", "recordid": "af1ef31f42446571b4f19a6bf5f2d408fb580f3c", "fields": {"municipality": "Barcelos", "extractiondatetime": "2024-04-01T17:18:00+00:00", "zipcode": "4750-725", "municipalitycode": "0302", "interrupcao_ativa": 1}}, {"datasetid": "outages-per-geography", "recordid": "cc1be30b44973cd7c0f87478dc2305919fee35dc", "fields": {"municipality": "Barcelos", "extractiondatetime": "2024-04-01T17:18:00+00:00", "zipcode": "4750-757", "municipalitycode": "0302", "interrupcao_ativa": 1}}, {"datasetid": "outages-per-geography", "recordid": "69d29be601f1e17f55fb659bc1f15de17c1c07dc", "fields": {"municipality": "Lisboa", "extractiondatetime": "2024-04-01T17:18:00+00:00", "zipcode": "1150-163", "municipalitycode": "1106", "interrupcao_ativa": 1}}, {"datasetid": "outages-per-geography", "recordid": "6fb781ff0541fce73880f75433720041b856f804", "fields": {"municipality": "Lisboa", "extractiondatetime": "2024-04-01T17:18:00+00:00", "zipcode": "1150-286", "municipalitycode": "1106", "interrupcao_ativa": 1}}, {"datasetid": "outages-per-geography", "recordid": "e5a79d8a9904fa070ee0aa5af05bce5e5effa159", "fields": {"municipality": "Barcelos", "extractiondatetime": "2024-04-01T17:18:00+00:00", "zipcode": "4750-063", "municipalitycode": "0302", "interrupcao_ativa": 1}}, {"datasetid": "outages-per-geography", "recordid": "67937144fd2921c204c2beaf2416b287baa49948", "fields": {"municipality": "Barcelos", "extractiondatetime": "2024-04-01T17:18:00+00:00", "zipcode": "4750-108", "municipalitycode": "0302", "interrupcao_ativa": 1}}], "facet_groups": [{"name": "zipcode", "facets": [{"name": "1150-111", "count": 1, "state": "displayed", "path": "1150-111"}, {"name": "1150-120", "count": 1, "state": "displayed", "path": "1150-120"}, {"name": "1150-121", "count": 1, "state": "displayed", "path": "1150-121"}, {"name": "1150-163", "count": 1, "state": "displayed", "path": "1150-163"}, {"name": "1150-229", "count": 1, "state": "displayed", "path": "1150-229"}, {"name": "1150-230", "count": 1, "state": "displayed", "path": "1150-230"}, {"name": "1150-231", "count": 1, "state": "displayed", "path": "1150-231"}, {"name": "1150-286", "count": 1, "state": "displayed", "path": "1150-286"}, {"name": "1150-310", "count": 1, "state": "displayed", "path": "1150-310"}, {"name": "1150-311", "count": 1, "state": "displayed", "path": "1150-311"}, {"name": "1150-343", "count": 1, "state": "displayed", "path": "1150-343"}, {"name": "4750-063", "count": 1, "state": "displayed", "path": "4750-063"}, {"name": "4750-108", "count": 1, "state": "displayed", "path": "4750-108"}, {"name": "4750-125", "count": 1, "state": "displayed", "path": "4750-125"}, {"name": "4750-147", "count": 1, "state": "displayed", "path": "4750-147"}, {"name": "4750-166", "count": 1, "state": "displayed", "path": "4750-166"}, {"name": "4750-464", "count": 1, "state": "displayed", "path": "4750-464"}, {"name": "4750-543", "count": 1, "state": "displayed", "path": "4750-543"}, {"name": "4750-722", "count": 1, "state": "displayed", "path": "4750-722"}, {"name": "4750-724", "count": 1, "state": "displayed", "path": "4750-724"}, {"name": "4750-725", "count": 1, "state": "displayed", "path": "4750-725"}, {"name": "4750-757", "count": 1, "state": "displayed", "path": "4750-757"}, {"name": "4750-784", "count": 1, "state": "displayed", "path": "4750-784"}]}, {"name": "municipality", "facets": [{"name": "Barcelos", "count": 12, "state": "displayed", "path": "Barcelos"}, {"name": "Lisboa", "count": 11, "state": "displayed", "path": "Lisboa"}]}]}